tentaclio_databricks/__init__.py
tentaclio_databricks/__main__.py
tentaclio_databricks/clients/__init__.py
tentaclio_databricks/clients/databricks_client.py
tentaclio_databricks-1.0.2.dist-info/LICENSE.txt
tentaclio_databricks-1.0.2.dist-info/METADATA
tentaclio_databricks-1.0.2.dist-info/WHEEL
tentaclio_databricks-1.0.2.dist-info/top_level.txt
tentaclio_databricks-1.0.2.dist-info/RECORD
